kegscraper/__init__.py
kegscraper/activelearn/__init__.py
kegscraper/activelearn/series.py
kegscraper/activelearn/session.py
kegscraper/bromcom/__init__.py
kegscraper/bromcom/session.py
kegscraper/bromcom/timetable.py
kegscraper/it/__init__.py
kegscraper/it/article.py
kegscraper/it/images.py
kegscraper/it/news.py
kegscraper/kerboodle/__init__.py
kegscraper/kerboodle/course.py
kegscraper/kerboodle/digitalbook.py
kegscraper/kerboodle/session.py
kegscraper/ms365/__init__.py
kegscraper/ms365/session.py
kegscraper/oliver/__init__.py
kegscraper/oliver/news.py
kegscraper/oliver/utils.py
kegscraper/papercut/__init__.py
kegscraper/papercut/org.py
kegscraper/papercut/session.py
kegscraper/site/__init__.py
kegscraper/site/asset.py
kegscraper/site/event_pdf_reader.py
kegscraper/site/events.py
kegscraper/util/__init__.py
kegscraper/util/commons.py
kegscraper/util/exceptions.py
kegscraper/vle/__init__.py
kegscraper/vle/blog.py
kegscraper/vle/calendar.py
kegscraper/vle/course.py
kegscraper/vle/coursecategory.py
kegscraper/vle/file.py
kegscraper/vle/forum.py
kegscraper/vle/session.py
kegscraper/vle/tag.py
kegscraper/vle/user.py
kegscraper-0.1.24.dist-info/WHEEL
kegscraper-0.1.24.dist-info/METADATA
kegscraper-0.1.24.dist-info/RECORD
