Metadata-Version: 2.4
Name: kegscraper
Version: 0.1.24
Summary: The ultimate KEGS webscraping module
Author: BigPotatoPizzaHey
Author-email: BigPotatoPizzaHey <poo@gmail.com>
License-Expression: Unlicense
Requires-Dist: beautifulsoup4~=4.12.3
Requires-Dist: bs4~=0.0.2
Requires-Dist: dateparser~=1.2.0
Requires-Dist: lxml~=5.4.0
Requires-Dist: pypdf~=5.1.0
Requires-Dist: pyperclip~=1.9.0
Requires-Dist: requests~=2.32.3
Requires-Dist: setuptools~=75.6.0
Requires-Dist: typing-extensions~=4.13.2
Requires-Dist: playwright>=1.57.0 ; extra == 'all'
Requires-Python: >=3.10.11
Project-URL: Documentation, https://github.com/BigPotatoPizzaHey/kegscraper/wiki
Project-URL: Homepage, https://kegs.org.uk/
Project-URL: Source, https://github.com/BigPotatoPizzaHey/kegscraper
Provides-Extra: all
